pytempmail/__init__.py
pytempmail/consts.py
pytempmail/emailid.py
pytempmail/excep.py
pytempmail/inbox.py
pytempmail/mail.py
pytempmail/tempmail.py
pytempmail/tempmailapi.py
pytempmail/testgen.py
pytempmail/timer.py
PyTempMail-0.1.dist-info/LICENSE
PyTempMail-0.1.dist-info/METADATA
PyTempMail-0.1.dist-info/WHEEL
PyTempMail-0.1.dist-info/top_level.txt
PyTempMail-0.1.dist-info/RECORD
