Metadata-Version: 2.1
Name: PyTempMail
Version: 0.1
Summary: Unoffical Python binding for TempMail website
Home-page: https://github.com/Shivanshu10/PyTempMail
Author: Shivanshu Mishra
License: UNKNOWN
Platform: UNKNOWN
Classifier: Programming Language :: Python :: 3
Classifier: License :: OSI Approved :: MIT License
Classifier: Operating System :: OS Independent
Requires-Python: >=3.6
Requires-Dist: selenium
